ZSI/ServiceContainer.py
ZSI/ServiceProxy.py
ZSI/TC.py
ZSI/TCapache.py
ZSI/TCcompound.py
ZSI/TCnumbers.py
ZSI/TCtimes.py
ZSI/__init__.py
ZSI/address.py
ZSI/auth.py
ZSI/client.py
ZSI/digest_auth.py
ZSI/dispatch.py
ZSI/fault.py
ZSI/parse.py
ZSI/resolvers.py
ZSI/schema.py
ZSI/typeinterpreter.py
ZSI/version.py
ZSI/writer.py
ZSI/generate/__init__.py
ZSI/generate/commands.py
ZSI/generate/containers.py
ZSI/generate/pyclass.py
ZSI/generate/utility.py
ZSI/generate/wsdl2dispatch.py
ZSI/generate/wsdl2python.py
ZSI/twisted/WSresource.py
ZSI/twisted/WSsecurity.py
ZSI/twisted/__init__.py
ZSI/twisted/client.py
ZSI/twisted/interfaces.py
ZSI/twisted/reverse.py
ZSI/twisted/wsgi.py
ZSI/wstools/MIMEAttachment.py
ZSI/wstools/Namespaces.py
ZSI/wstools/TimeoutSocket.py
ZSI/wstools/UserTuple.py
ZSI/wstools/Utility.py
ZSI/wstools/WSDLTools.py
ZSI/wstools/XMLSchema.py
ZSI/wstools/XMLname.py
ZSI/wstools/__init__.py
ZSI/wstools/c14n.py
ZSI/wstools/logging.py
PyZSI3-2.2.dist-info/METADATA
PyZSI3-2.2.dist-info/WHEEL
PyZSI3-2.2.dist-info/dependency_links.txt
PyZSI3-2.2.dist-info/entry_points.txt
PyZSI3-2.2.dist-info/top_level.txt
PyZSI3-2.2.dist-info/RECORD
