Metadata-Version: 2.1
Name: PyZSI3
Version: 2.2
Summary: Zolera SOAP Infrastructure
Home-page: http://pywebsvcs.sf.net/
Author: Rich Salz, et al
Author-email: rsalz@datapower.com
Maintainer: Rich Salz, et al
Maintainer-email: pywebsvcs-talk@lists.sf.net
License: Python
